gandi.cli-1.6-nspkg.pth
gandi/cli/__init__.py
gandi/cli/__main__.py
gandi/cli/commands/__init__.py
gandi/cli/commands/account.py
gandi/cli/commands/certificate.py
gandi/cli/commands/certstore.py
gandi/cli/commands/config.py
gandi/cli/commands/contact.py
gandi/cli/commands/disk.py
gandi/cli/commands/dns.py
gandi/cli/commands/dnssec.py
gandi/cli/commands/docker.py
gandi/cli/commands/domain.py
gandi/cli/commands/forward.py
gandi/cli/commands/ip.py
gandi/cli/commands/mail.py
gandi/cli/commands/oper.py
gandi/cli/commands/paas.py
gandi/cli/commands/record.py
gandi/cli/commands/root.py
gandi/cli/commands/snapshotprofile.py
gandi/cli/commands/sshkey.py
gandi/cli/commands/vhost.py
gandi/cli/commands/vlan.py
gandi/cli/commands/vm.py
gandi/cli/commands/webacc.py
gandi/cli/core/__init__.py
gandi/cli/core/base.py
gandi/cli/core/cli.py
gandi/cli/core/client.py
gandi/cli/core/conf.py
gandi/cli/core/params.py
gandi/cli/core/utils/__init__.py
gandi/cli/core/utils/ascii_sparks.py
gandi/cli/core/utils/password.py
gandi/cli/core/utils/size.py
gandi/cli/core/utils/unixpipe.py
gandi/cli/core/utils/xmlrpc.py
gandi/cli/modules/__init__.py
gandi/cli/modules/account.py
gandi/cli/modules/api.py
gandi/cli/modules/cert.py
gandi/cli/modules/contact.py
gandi/cli/modules/datacenter.py
gandi/cli/modules/disk.py
gandi/cli/modules/dns.py
gandi/cli/modules/dnssec.py
gandi/cli/modules/docker.py
gandi/cli/modules/domain.py
gandi/cli/modules/forward.py
gandi/cli/modules/hostedcert.py
gandi/cli/modules/iaas.py
gandi/cli/modules/mail.py
gandi/cli/modules/metric.py
gandi/cli/modules/network.py
gandi/cli/modules/oper.py
gandi/cli/modules/paas.py
gandi/cli/modules/record.py
gandi/cli/modules/snapshotprofile.py
gandi/cli/modules/sshkey.py
gandi/cli/modules/status.py
gandi/cli/modules/vhost.py
gandi/cli/modules/webacc.py
gandi/cli/tests/__init__.py
gandi/cli/tests/compat.py
gandi/cli/tests/test_main.py
gandi/cli/tests/commands/__init__.py
gandi/cli/tests/commands/base.py
gandi.cli-1.6.dist-info/LICENSE
gandi.cli-1.6.dist-info/METADATA
gandi.cli-1.6.dist-info/WHEEL
gandi.cli-1.6.dist-info/entry_points.txt
gandi.cli-1.6.dist-info/namespace_packages.txt
gandi.cli-1.6.dist-info/top_level.txt
gandi.cli-1.6.dist-info/RECORD
